{
  "cast_delay_ms": 300,
  "description": {
    "translate": "mirthdew_encore.card_spell.mirthdew_encore.fire_arrow"
  },
  "effects": {
    "mirthdew_encore:fire_entity": [
      {
        "entity": [
          "minecraft:arrow"
        ],
        "speed": 1.8,
        "divergence": 6.0,
        "nbt": {
          "item":{
            "count":1,
            "id":"minecraft:arrow",
            "components": {
              "minecraft:intangible_projectile":{}
            }
          },
          "pickup": 2
        }
      }
    ]
  },
  "input_count": 0,
  "mirth_cost": 12,
  "recharge_delay_ms": 60
}